csoundengine/__init__.py
csoundengine/__sessionbase.py
csoundengine/_common.py
csoundengine/_palette.py
csoundengine/abstractrenderer.py
csoundengine/baseschedevent.py
csoundengine/busproxy.py
csoundengine/config.py
csoundengine/contants.py
csoundengine/csd.py
csoundengine/csoundlib.py
csoundengine/csoundparse.py
csoundengine/dependencies.py
csoundengine/engine.py
csoundengine/enginebase.py
csoundengine/engineorc.py
csoundengine/errors.py
csoundengine/event.py
csoundengine/instr.py
csoundengine/instrtools.py
csoundengine/interact.py
csoundengine/internal.py
csoundengine/jacktools.py
csoundengine/jupytertools.py
csoundengine/linuxaudio.py
csoundengine/magic.py
csoundengine/offline.py
csoundengine/offlineengine.py
csoundengine/offlineorc.py
csoundengine/paramtable.py
csoundengine/plotting.py
csoundengine/py.typed
csoundengine/renderjob.py
csoundengine/schedevent.py
csoundengine/session.py
csoundengine/sessionhandler.py
csoundengine/sessioninstrs.py
csoundengine/sftools.py
csoundengine/state.py
csoundengine/synth.py
csoundengine/tableproxy.py
csoundengine/termui.py
csoundengine/tools.py
csoundengine/data/plugins6/linux-x86_64/libbeosc.so
csoundengine/data/plugins6/linux-x86_64/libelse.so
csoundengine/data/plugins6/linux-x86_64/libjsfx.so
csoundengine/data/plugins6/linux-x86_64/libklib.so
csoundengine/data/plugins6/linux-x86_64/libpathtools.so
csoundengine/data/plugins6/linux-x86_64/libpoly.so
csoundengine/data/plugins6/linux-x86_64/libpoodle.so
csoundengine/data/plugins6/linux-x86_64/librisset.so
csoundengine/data/plugins6/linux-x86_64/libsndmeta.so
csoundengine/data/plugins6/macos-arm64/libbeosc.dylib
csoundengine/data/plugins6/macos-arm64/libelse.dylib
csoundengine/data/plugins6/macos-arm64/libklib.dylib
csoundengine/data/plugins6/macos-arm64/libpathtools.dylib
csoundengine/data/plugins6/macos-arm64/libpoly.dylib
csoundengine/data/plugins6/macos-arm64/librisset.dylib
csoundengine/data/plugins6/macos-x86_64/libbeosc.dylib
csoundengine-2.21.5.dist-info/licenses/LICENSE.txt
csoundengine-2.21.5.dist-info/METADATA
csoundengine-2.21.5.dist-info/WHEEL
csoundengine-2.21.5.dist-info/top_level.txt
csoundengine-2.21.5.dist-info/RECORD
