Metadata-Version: 2.4
Name: csoundengine
Version: 2.21.5
Summary: An audio synthesis framework using csound
Author-email: Eduardo Moguillansky <eduardo.moguillansky@gmail.com>
License: GNU GENERAL PUBLIC LICENSE
Project-URL: Homepage, https://github.com/gesellkammer/csoundengine
Classifier: Programming Language :: Python :: 3
Classifier: Operating System :: OS Independent
Requires-Python: >=3.9
License-File: LICENSE.txt
Requires-Dist: numpy
Requires-Dist: scipy
Requires-Dist: matplotlib
Requires-Dist: cachetools
Requires-Dist: JACK-client
Requires-Dist: appdirs
Requires-Dist: pygments
Requires-Dist: sf2utils13
Requires-Dist: ipywidgets
Requires-Dist: xxhash
Requires-Dist: docstring_parser
Requires-Dist: typing_extensions
Requires-Dist: libcsound>=0.11.1
Requires-Dist: sndfileio>=2.1.1
Requires-Dist: emlib>=1.20
Requires-Dist: configdict>=2.10.0
Requires-Dist: pitchtools>=1.14.0
Requires-Dist: risset>=3.2.2
Requires-Dist: sounddevice
Dynamic: license-file
